async_utils/__init__.py
async_utils/_paramkey.py
async_utils/_qs.py
async_utils/_typings.py
async_utils/bg_loop.py
async_utils/bg_tasks.py
async_utils/corofunc_cache.py
async_utils/dual_color.py
async_utils/gen_transform.py
async_utils/lockout.py
async_utils/lru.py
async_utils/priority_sem.py
async_utils/py.typed
async_utils/ratelimiter.py
async_utils/scheduler.py
async_utils/sig_service.py
async_utils/task_cache.py
async_utils/waterfall.py
mikeshardmind_async_utils-2025.6.8b0.dist-info/METADATA
mikeshardmind_async_utils-2025.6.8b0.dist-info/WHEEL
mikeshardmind_async_utils-2025.6.8b0.dist-info/entry_points.txt
mikeshardmind_async_utils-2025.6.8b0.dist-info/licenses/LICENSE
mikeshardmind_async_utils-2025.6.8b0.dist-info/licenses/NOTICE
mikeshardmind_async_utils-2025.6.8b0.dist-info/RECORD
