Metadata-Version: 2.1
Name: mikeshardmind-async-utils
Version: 2025.6.8b0
Summary: Various async utilities
Author-Email: Michael Hall <michael@michaelhall.tech>
License: Apache-2.0
Classifier: Intended Audience :: Developers
Classifier: Operating System :: OS Independent
Classifier: Typing :: Typed
Classifier: Programming Language :: Python :: Implementation :: CPython
Classifier: Framework :: AsyncIO
Classifier: Intended Audience :: Developers
Classifier: Natural Language :: English
Classifier: Typing :: Typed
Classifier: Programming Language :: Python :: 3 :: Only
Classifier: Programming Language :: Python :: 3.12
Classifier: Programming Language :: Python :: 3.13
Project-URL: Homepage, https://github.com/mikeshardmind/async-utils
Project-URL: Issue Tracker, https://github.com/mikeshardmind/async-utils/issues
Project-URL: Source Code, https://github.com/mikeshardmind/async-utils
Requires-Python: >=3.12.0
